falcon_arch/__init__.py
falcon_arch/__version__.py
falcon_arch/falcon_arch.py
falcon_arch/logger.py
falcon_arch/router.py
falcon_arch/exceptions/__init__.py
falcon_arch/exceptions/http_exception.py
falcon_arch/exceptions/http_exception_helper.py
falcon_arch/helps/__init__.py
falcon_arch/helps/_error.py
falcon_arch/helps/_screen.py
falcon_arch/http/__init__.py
falcon_arch/http/request.py
falcon_arch/http/response.py
falcon_arch-0.1.0.dist-info/licenses/LICENSE
falcon_arch-0.1.0.dist-info/METADATA
falcon_arch-0.1.0.dist-info/WHEEL
falcon_arch-0.1.0.dist-info/top_level.txt
falcon_arch-0.1.0.dist-info/RECORD
