Metadata-Version: 2.4
Name: falcon-arch
Version: 0.1.0
Summary: FalconArch is a lightweight and modular library that provides a base structure for developing applications with Flask.
Home-page: https://github.com/celiovmjr/falcon-arch
Author: Célio Junior
Author-email: profissional.celiojunior@outlook.com
Classifier: Programming Language :: Python :: 3
Classifier: License :: OSI Approved :: MIT License
Classifier: Operating System :: OS Independent
Requires-Python: >=3.6
License-File: LICENSE
Requires-Dist: Flask>=3.1.0
Requires-Dist: waitress>=3.0.2
Dynamic: author
Dynamic: author-email
Dynamic: classifier
Dynamic: description
Dynamic: description-content-type
Dynamic: home-page
Dynamic: license-file
Dynamic: requires-dist
Dynamic: requires-python
Dynamic: summary
